physam/__init__.py
physam/cli.py
physam/sspps/__init__.py
physam/sspps/optimal_spps_subsets.py
physam/sspps/random_spps_subsets.py
physam/sspps/utils.py
physam/sspps/variables.py
physam-0.3.dist-info/METADATA
physam-0.3.dist-info/WHEEL
physam-0.3.dist-info/entry_points.txt
physam-0.3.dist-info/top_level.txt
physam-0.3.dist-info/RECORD
