Metadata-Version: 2.1
Name: physam
Version: 0.3
Summary: UNKNOWN
Home-page: UNKNOWN
Maintainer: Ulises Rosas
License: UNKNOWN
Platform: UNKNOWN
Classifier: Programming Language :: Python :: 3
Requires-Python: >=3
Requires-Dist: cvxopt
Requires-Dist: cvxpy
